{
	"configurations" : 
	[
		{
			"directories" : 
			[
				{
					"build" : ".",
					"jsonFile" : "directory-.-Debug-f5ebdc15457944623624.json",
					"minimumCMakeVersion" : 
					{
						"string" : "3.22"
					},
					"projectIndex" : 0,
					"source" : ".",
					"targetIndexes" : 
					[
						0
					]
				}
			],
			"name" : "Debug",
			"projects" : 
			[
				{
					"directoryIndexes" : 
					[
						0
					],
					"name" : "CPP_09",
					"targetIndexes" : 
					[
						0
					]
				}
			],
			"targets" : 
			[
				{
					"directoryIndex" : 0,
					"id" : "CPP_09::@6890427a1f51a3e7e1df",
					"jsonFile" : "target-CPP_09-Debug-2a40411201af0a51bcf0.json",
					"name" : "CPP_09",
					"projectIndex" : 0
				}
			]
		}
	],
	"kind" : "codemodel",
	"paths" : 
	{
		"build" : "/Users/rmazurit/Documents/42_Projects/cpp_modules/CPP_09/cmake-build-debug",
		"source" : "/Users/rmazurit/Documents/42_Projects/cpp_modules/CPP_09"
	},
	"version" : 
	{
		"major" : 2,
		"minor" : 4
	}
}
